[
	{
		"id_tag": "PID_\u795e\u968e\u30f4\u30a7\u30a4\u30eb",
		"roman": "VEYRE_GOD01",
		"face_name": "ch19_35_Veyre_F_God01",
		"face_name2": "ch19_35_Veyre_F_God01",
		"legendary": {
			"duo_skill_id": "",
			"bonus_effect": {
				"hp": 5,
				"atk": 0,
				"spd": 0,
				"def": 5,
				"res": 0
			},
			"kind": 1,
			"element": 7,
			"bst": 0,
			"pair_up": false,
			"ae_extra": true
		},
		"dragonflowers": {
			"max_count": 5,
			"costs": [
				40,
				80,
				120,
				160,
				200
			]
		},
		"timestamp": null,
		"id_num": 1015,
		"version_num": 710,
		"sort_value": 900200,
		"origins": 16384,
		"weapon_type": 12,
		"tome_class": 2,
		"move_type": 0,
		"series": 14,
		"random_pool": 0,
		"permanent_hero": false,
		"base_vactor_id": 182,
		"refresher": false,
		"base_stats": {
			"hp": 17,
			"atk": 16,
			"spd": 8,
			"def": 4,
			"res": 7
		},
		"growth_rates": {
			"hp": 50,
			"atk": 70,
			"spd": 50,
			"def": 40,
			"res": 90
		},
		"skills": [
			[
				"SID_\u30b5\u30f3\u30c0\u30fc",
				null,
				null,
				null,
				null,
				null,
				null,
				null,
				null,
				null,
				null,
				null,
				null,
				null,
				null
			],
			[
				"SID_\u30a8\u30eb\u30b5\u30f3\u30c0\u30fc",
				null,
				null,
				null,
				null,
				null,
				null,
				null,
				null,
				null,
				"SID_\u653b\u6483\u9b54\u9632\u306e\u79d8\u59651",
				"SID_\u653b\u6483\u9b54\u9632\u306e\u62cd\u7bc01",
				null,
				null,
				null
			],
			[
				"SID_\u30a8\u30eb\u30b5\u30f3\u30c0\u30fc",
				null,
				null,
				null,
				null,
				null,
				null,
				"SID_\u30c8\u30ed\u30f3",
				null,
				"SID_\u6c37\u70b9",
				"SID_\u653b\u6483\u9b54\u9632\u306e\u79d8\u59652",
				"SID_\u653b\u6483\u9b54\u9632\u306e\u62cd\u7bc02",
				null,
				null,
				null
			],
			[
				"SID_\u30c8\u30ed\u30f3",
				null,
				"SID_\u6c37\u70b9",
				null,
				null,
				null,
				null,
				null,
				null,
				"SID_\u6c37\u84bc",
				"SID_\u653b\u6483\u9b54\u9632\u306e\u79d8\u59653",
				"SID_\u653b\u6483\u9b54\u9632\u306e\u62cd\u7bc03",
				null,
				null,
				null
			],
			[
				"SID_\u30aa\u30f4\u30b9\u30ad\u30e5\u30ea\u30c6",
				null,
				"SID_\u6c37\u70b9",
				null,
				null,
				null,
				null,
				null,
				null,
				null,
				"SID_\u653b\u6483\u9b54\u9632\u306e\u79d8\u59654",
				"SID_\u653b\u6483\u9b54\u9632\u306e\u62cd\u7bc04",
				"SID_\u90aa\u7adc\u306e\u6551\u6e08",
				null,
				null
			]
		]
	}
]